[
    {
        "signature": "21oGo1s9j6LAMMTRByKzVTMF4mCHRwAdtyWazQvZzm9rntRz8YPBEnU6jFauHTzwKwyyFGFFXeTCsPtYRkqYLJXm",
        "block": 385526373,
        "timestamp": "2025-06-05 09:39:00",
        "version": "legacy",
        "fee_in_sol": 5e-06,
        "compute_units_consumed": 150,
        "previous_block_hash": "GYiEUxgPaHjBXHqc2i6ayZpbXVNN8LEWEPdrqy5p3YpU",
        "signers": [],
        "from": {
            "address": "4PkiqJkUvxr9P8C1UsMqGN8NJsUcep9GahDRLfmeu8UK",
            "balance_before": 10.402096649,
            "balance_after": 10.40209163,
            "balance_change": -5.019e-06
        },
        "to": [
            {
                "address": "ANVUJaJoVaJZELtV2AvRp7V5qPV1B84o29zAwDhPj1c2",
                "balance_before": 10.402096649,
                "balance_after": 10.40209163,
                "balance_change": 5.019e-06
            }
        ],
        "instructions": [
            {
                "program_id": "11111111111111111111111111111111",
                "type": "transfer",
                "info": {
                    "destination": "ANVUJaJoVaJZELtV2AvRp7V5qPV1B84o29zAwDhPj1c2",
                    "lamports": 19,
                    "source": "4PkiqJkUvxr9P8C1UsMqGN8NJsUcep9GahDRLfmeu8UK"
                }
            }
        ]
    },
    {
        "signature": "65qaKVtbY4inT3Gs4Hvs9qPWoU7fma16cgKbXSDU7yaGYYinSNjgngTVuABxr5C9sPu1ZM86M5EAp6VNUNWsFxYM",
        "block": 385526373,
        "timestamp": "2025-06-05 09:39:00",
        "version": "legacy",
        "fee_in_sol": 5e-06,
        "compute_units_consumed": 150,
        "previous_block_hash": "66r6iyX3GEMNh5V66jSjgHqnoYm19b5VotkX3VaFvs1T",
        "signers": [],
        "from": {
            "address": "4PkiqJkUvxr9P8C1UsMqGN8NJsUcep9GahDRLfmeu8UK",
            "balance_before": 10.402101654,
            "balance_after": 10.402096649,
            "balance_change": -5.005e-06
        },
        "to": [
            {
                "address": "ANVUJaJoVaJZELtV2AvRp7V5qPV1B84o29zAwDhPj1c2",
                "balance_before": 10.402101654,
                "balance_after": 10.402096649,
                "balance_change": 5.005e-06
            }
        ],
        "instructions": [
            {
                "program_id": "11111111111111111111111111111111",
                "type": "transfer",
                "info": {
                    "destination": "ANVUJaJoVaJZELtV2AvRp7V5qPV1B84o29zAwDhPj1c2",
                    "lamports": 5,
                    "source": "4PkiqJkUvxr9P8C1UsMqGN8NJsUcep9GahDRLfmeu8UK"
                }
            }
        ]
    },
    {
        "signature": "615qviP7QowKohr4uHmHZZ61wUFo7HquGZzCuF7po998Lafsmdh6f55bpKZbamwuv2ysNYJuKjKz3b3NzbKn8KV8",
        "block": 385526373,
        "timestamp": "2025-06-05 09:39:00",
        "version": "legacy",
        "fee_in_sol": 5e-06,
        "compute_units_consumed": 150,
        "previous_block_hash": "6qi14kXaHH8tXc9z82e7LHsW8hyY9zCe8RAJzVX4xtXL",
        "signers": [],
        "from": {
            "address": "4PkiqJkUvxr9P8C1UsMqGN8NJsUcep9GahDRLfmeu8UK",
            "balance_before": 10.402106675,
            "balance_after": 10.402101654,
            "balance_change": -5.021e-06
        },
        "to": [
            {
                "address": "ANVUJaJoVaJZELtV2AvRp7V5qPV1B84o29zAwDhPj1c2",
                "balance_before": 10.402106675,
                "balance_after": 10.402101654,
                "balance_change": 5.021e-06
            }
        ],
        "instructions": [
            {
                "program_id": "11111111111111111111111111111111",
                "type": "transfer",
                "info": {
                    "destination": "ANVUJaJoVaJZELtV2AvRp7V5qPV1B84o29zAwDhPj1c2",
                    "lamports": 21,
                    "source": "4PkiqJkUvxr9P8C1UsMqGN8NJsUcep9GahDRLfmeu8UK"
                }
            }
        ]
    },
    {
        "signature": "395m9ujZWAFR33HfdpszUFUG4ERLHJYVkuke8qf3Q91WxJVFKwtZ3iQ5ddRdtnex7y93HGTHBEaPv6HRQ3XqhpR4",
        "block": 385526373,
        "timestamp": "2025-06-05 09:39:00",
        "version": "legacy",
        "fee_in_sol": 5e-06,
        "compute_units_consumed": 150,
        "previous_block_hash": "7oQjvyfKfJ7Z16UyvNpeMr5qVnpGDZdLRbPvC39THqGu",
        "signers": [],
        "from": {
            "address": "4PkiqJkUvxr9P8C1UsMqGN8NJsUcep9GahDRLfmeu8UK",
            "balance_before": 10.402111678,
            "balance_after": 10.402106675,
            "balance_change": -5.003e-06
        },
        "to": [
            {
                "address": "ANVUJaJoVaJZELtV2AvRp7V5qPV1B84o29zAwDhPj1c2",
                "balance_before": 10.402111678,
                "balance_after": 10.402106675,
                "balance_change": 5.003e-06
            }
        ],
        "instructions": [
            {
                "program_id": "11111111111111111111111111111111",
                "type": "transfer",
                "info": {
                    "destination": "ANVUJaJoVaJZELtV2AvRp7V5qPV1B84o29zAwDhPj1c2",
                    "lamports": 3,
                    "source": "4PkiqJkUvxr9P8C1UsMqGN8NJsUcep9GahDRLfmeu8UK"
                }
            }
        ]
    },
    {
        "signature": "4EHv3vrHtw4VhqTZb7FExF1Yx4bspe98w7CxJqNb9fUKQ4TaRaMzgVHHiigt17DTrB9mHfwU86fwRLn8MMNkFNYM",
        "block": 385526373,
        "timestamp": "2025-06-05 09:39:00",
        "version": "legacy",
        "fee_in_sol": 5e-06,
        "compute_units_consumed": 150,
        "previous_block_hash": "9pgTgA9StCHjowr18Tb58XGoWcJmhYmCzdxoeAGtaEhL",
        "signers": [],
        "from": {
            "address": "ANVUJaJoVaJZELtV2AvRp7V5qPV1B84o29zAwDhPj1c2",
            "balance_before": 1.819705566,
            "balance_after": 1.819700558,
            "balance_change": -5.008e-06
        },
        "to": [
            {
                "address": "4PkiqJkUvxr9P8C1UsMqGN8NJsUcep9GahDRLfmeu8UK",
                "balance_before": 1.819705566,
                "balance_after": 1.819700558,
                "balance_change": 5.008e-06
            }
        ],
        "instructions": [
            {
                "program_id": "11111111111111111111111111111111",
                "type": "transfer",
                "info": {
                    "destination": "4PkiqJkUvxr9P8C1UsMqGN8NJsUcep9GahDRLfmeu8UK",
                    "lamports": 8,
                    "source": "ANVUJaJoVaJZELtV2AvRp7V5qPV1B84o29zAwDhPj1c2"
                }
            }
        ]
    },
    {
        "signature": "4yyXMe11ywY6oJXZ9hHWAdfLgBsyXc6D7eDzetLWLTutaFXBSzKf5D8L7zKW6fk7j9i1xZ8SA4p4e54LZNuDQXSC",
        "block": 385526372,
        "timestamp": "2025-06-05 09:38:59",
        "version": "legacy",
        "fee_in_sol": 5e-06,
        "compute_units_consumed": 150,
        "previous_block_hash": "4JmXTZf9buNdsVy69HDL8kDxrvLcvkbiDgW57HY218oN",
        "signers": [],
        "from": {
            "address": "4PkiqJkUvxr9P8C1UsMqGN8NJsUcep9GahDRLfmeu8UK",
            "balance_before": 10.402116685,
            "balance_after": 10.40211167,
            "balance_change": -5.015e-06
        },
        "to": [
            {
                "address": "ANVUJaJoVaJZELtV2AvRp7V5qPV1B84o29zAwDhPj1c2",
                "balance_before": 10.402116685,
                "balance_after": 10.40211167,
                "balance_change": 5.015e-06
            }
        ],
        "instructions": [
            {
                "program_id": "11111111111111111111111111111111",
                "type": "transfer",
                "info": {
                    "destination": "ANVUJaJoVaJZELtV2AvRp7V5qPV1B84o29zAwDhPj1c2",
                    "lamports": 15,
                    "source": "4PkiqJkUvxr9P8C1UsMqGN8NJsUcep9GahDRLfmeu8UK"
                }
            }
        ]
    },
    {
        "signature": "4uDRPajvcnxb7yBoixMuhUdZiUphUBTdgR7AKga6mpxgkRcuNPiTXpxWHZRUcm1Q411hg4LdH7eCGs39uF9xbdWa",
        "block": 385526372,
        "timestamp": "2025-06-05 09:38:59",
        "version": "legacy",
        "fee_in_sol": 5e-06,
        "compute_units_consumed": 150,
        "previous_block_hash": "D1F9SLjpqkUGfx3FjFYaAbuTo7Bber5RxqExZ8NbPza2",
        "signers": [],
        "from": {
            "address": "4PkiqJkUvxr9P8C1UsMqGN8NJsUcep9GahDRLfmeu8UK",
            "balance_before": 10.402121698,
            "balance_after": 10.402116685,
            "balance_change": -5.013e-06
        },
        "to": [
            {
                "address": "ANVUJaJoVaJZELtV2AvRp7V5qPV1B84o29zAwDhPj1c2",
                "balance_before": 10.402121698,
                "balance_after": 10.402116685,
                "balance_change": 5.013e-06
            }
        ],
        "instructions": [
            {
                "program_id": "11111111111111111111111111111111",
                "type": "transfer",
                "info": {
                    "destination": "ANVUJaJoVaJZELtV2AvRp7V5qPV1B84o29zAwDhPj1c2",
                    "lamports": 13,
                    "source": "4PkiqJkUvxr9P8C1UsMqGN8NJsUcep9GahDRLfmeu8UK"
                }
            }
        ]
    },
    {
        "signature": "3XDot1hoc35EHMiaUNibPVsPGAth64N9amCnX38Xu3E3hiPHySQuhmXBnvBmo25fEhcra5L4nsUZ59PU4iErswxy",
        "block": 385526372,
        "timestamp": "2025-06-05 09:38:59",
        "version": "legacy",
        "fee_in_sol": 5e-06,
        "compute_units_consumed": 150,
        "previous_block_hash": "9mpoFNweGX853HXiQYJAr8KFpM5Gr6FVBuVTTgPFBHpn",
        "signers": [],
        "from": {
            "address": "4PkiqJkUvxr9P8C1UsMqGN8NJsUcep9GahDRLfmeu8UK",
            "balance_before": 10.402126699,
            "balance_after": 10.402121698,
            "balance_change": -5.001e-06
        },
        "to": [
            {
                "address": "ANVUJaJoVaJZELtV2AvRp7V5qPV1B84o29zAwDhPj1c2",
                "balance_before": 10.402126699,
                "balance_after": 10.402121698,
                "balance_change": 5.001e-06
            }
        ],
        "instructions": [
            {
                "program_id": "11111111111111111111111111111111",
                "type": "transfer",
                "info": {
                    "destination": "ANVUJaJoVaJZELtV2AvRp7V5qPV1B84o29zAwDhPj1c2",
                    "lamports": 1,
                    "source": "4PkiqJkUvxr9P8C1UsMqGN8NJsUcep9GahDRLfmeu8UK"
                }
            }
        ]
    },
    {
        "signature": "2CW5RfKy9QYbZmNQNqej8vfk2JNjdnTu7uLq3BSmxVeRb54TMqZ26irpY9EkwXvVVrwqYHEAR6QGXv1548zxNcj8",
        "block": 385526372,
        "timestamp": "2025-06-05 09:38:59",
        "version": "legacy",
        "fee_in_sol": 5e-06,
        "compute_units_consumed": 150,
        "previous_block_hash": "6oBNiMModUCpBMu95N2rb5ZLHdoNJFySq8THVK9xqDqA",
        "signers": [],
        "from": {
            "address": "ANVUJaJoVaJZELtV2AvRp7V5qPV1B84o29zAwDhPj1c2",
            "balance_before": 1.819710547,
            "balance_after": 1.819705537,
            "balance_change": -5.01e-06
        },
        "to": [
            {
                "address": "4PkiqJkUvxr9P8C1UsMqGN8NJsUcep9GahDRLfmeu8UK",
                "balance_before": 1.819710547,
                "balance_after": 1.819705537,
                "balance_change": 5.01e-06
            }
        ],
        "instructions": [
            {
                "program_id": "11111111111111111111111111111111",
                "type": "transfer",
                "info": {
                    "destination": "4PkiqJkUvxr9P8C1UsMqGN8NJsUcep9GahDRLfmeu8UK",
                    "lamports": 10,
                    "source": "ANVUJaJoVaJZELtV2AvRp7V5qPV1B84o29zAwDhPj1c2"
                }
            }
        ]
    },
    {
        "signature": "vprxo86TbePbZMrMPnWihpzpsZvunpBRmDSUUCmf5tq7HDz1Xd8faXThftjaRXDw9LY3q4GnHJLGn7ghoTHMxBk",
        "block": 385526372,
        "timestamp": "2025-06-05 09:38:59",
        "version": "legacy",
        "fee_in_sol": 5e-06,
        "compute_units_consumed": 150,
        "previous_block_hash": "6iNMerZJ9tHo94PpmDqdaRjn818NFkUbSxGR9qLuJtYJ",
        "signers": [],
        "from": {
            "address": "4PkiqJkUvxr9P8C1UsMqGN8NJsUcep9GahDRLfmeu8UK",
            "balance_before": 10.402131706,
            "balance_after": 10.402126689,
            "balance_change": -5.017e-06
        },
        "to": [
            {
                "address": "ANVUJaJoVaJZELtV2AvRp7V5qPV1B84o29zAwDhPj1c2",
                "balance_before": 10.402131706,
                "balance_after": 10.402126689,
                "balance_change": 5.017e-06
            }
        ],
        "instructions": [
            {
                "program_id": "11111111111111111111111111111111",
                "type": "transfer",
                "info": {
                    "destination": "ANVUJaJoVaJZELtV2AvRp7V5qPV1B84o29zAwDhPj1c2",
                    "lamports": 17,
                    "source": "4PkiqJkUvxr9P8C1UsMqGN8NJsUcep9GahDRLfmeu8UK"
                }
            }
        ]
    },
    {
        "signature": "5zzpLdXDoDRo9woZNfEK9RTuWBUfDmgBqoGQrcKaLQDPMbfwCrk986aCyy8SsqStjT8UxpxVK5RPbm8gdBhu7Aqu",
        "block": 385526371,
        "timestamp": "2025-06-05 09:38:59",
        "version": "legacy",
        "fee_in_sol": 5e-06,
        "compute_units_consumed": 150,
        "previous_block_hash": "GYiEUxgPaHjBXHqc2i6ayZpbXVNN8LEWEPdrqy5p3YpU",
        "signers": [],
        "from": {
            "address": "ANVUJaJoVaJZELtV2AvRp7V5qPV1B84o29zAwDhPj1c2",
            "balance_before": 1.819715542,
            "balance_after": 1.81971053,
            "balance_change": -5.012e-06
        },
        "to": [
            {
                "address": "4PkiqJkUvxr9P8C1UsMqGN8NJsUcep9GahDRLfmeu8UK",
                "balance_before": 1.819715542,
                "balance_after": 1.81971053,
                "balance_change": 5.012e-06
            }
        ],
        "instructions": [
            {
                "program_id": "11111111111111111111111111111111",
                "type": "transfer",
                "info": {
                    "destination": "4PkiqJkUvxr9P8C1UsMqGN8NJsUcep9GahDRLfmeu8UK",
                    "lamports": 12,
                    "source": "ANVUJaJoVaJZELtV2AvRp7V5qPV1B84o29zAwDhPj1c2"
                }
            }
        ]
    },
    {
        "signature": "qrVLjnE1PWy7UpsRGSCcwyt28PHxW4jFgQ7JU7uQZQMpLWEfzUpioJg2mebV8uJ6pgwv98QaqNGqHngEgDmPqs9",
        "block": 385526371,
        "timestamp": "2025-06-05 09:38:59",
        "version": "legacy",
        "fee_in_sol": 5e-06,
        "compute_units_consumed": 150,
        "previous_block_hash": "ERXs87zUz6rqVBrWpFgHz7Vn3MXWgb32h1ghUf8YgK4Q",
        "signers": [],
        "from": {
            "address": "ANVUJaJoVaJZELtV2AvRp7V5qPV1B84o29zAwDhPj1c2",
            "balance_before": 1.819720562,
            "balance_after": 1.819715542,
            "balance_change": -5.02e-06
        },
        "to": [
            {
                "address": "4PkiqJkUvxr9P8C1UsMqGN8NJsUcep9GahDRLfmeu8UK",
                "balance_before": 1.819720562,
                "balance_after": 1.819715542,
                "balance_change": 5.02e-06
            }
        ],
        "instructions": [
            {
                "program_id": "11111111111111111111111111111111",
                "type": "transfer",
                "info": {
                    "destination": "4PkiqJkUvxr9P8C1UsMqGN8NJsUcep9GahDRLfmeu8UK",
                    "lamports": 20,
                    "source": "ANVUJaJoVaJZELtV2AvRp7V5qPV1B84o29zAwDhPj1c2"
                }
            }
        ]
    },
    {
        "signature": "4ej6uFy8MKxeiLu7KqcTakZFdSsCP3DqfDwzLNa1suMibLuDXhwrYj4XKuRhLCGAAZFe9aqUhQ8hrEi2rxdW2EA",
        "block": 385526371,
        "timestamp": "2025-06-05 09:38:59",
        "version": "legacy",
        "fee_in_sol": 5e-06,
        "compute_units_consumed": 150,
        "previous_block_hash": "A8mFdZJirqpKLovdmaaN4RLQWke24HLShMz4h2BPEvRV",
        "signers": [],
        "from": {
            "address": "ANVUJaJoVaJZELtV2AvRp7V5qPV1B84o29zAwDhPj1c2",
            "balance_before": 1.819725578,
            "balance_after": 1.819720562,
            "balance_change": -5.016e-06
        },
        "to": [
            {
                "address": "4PkiqJkUvxr9P8C1UsMqGN8NJsUcep9GahDRLfmeu8UK",
                "balance_before": 1.819725578,
                "balance_after": 1.819720562,
                "balance_change": 5.016e-06
            }
        ],
        "instructions": [
            {
                "program_id": "11111111111111111111111111111111",
                "type": "transfer",
                "info": {
                    "destination": "4PkiqJkUvxr9P8C1UsMqGN8NJsUcep9GahDRLfmeu8UK",
                    "lamports": 16,
                    "source": "ANVUJaJoVaJZELtV2AvRp7V5qPV1B84o29zAwDhPj1c2"
                }
            }
        ]
    },
    {
        "signature": "5Curm8mSVZiKJiC2K38e867uqryAkp6JSU1UJrM5pGoUH816Ce5LwHez7ZFZh2fyHQtT2FFQTkZK4Q1h6si3jk8H",
        "block": 385526371,
        "timestamp": "2025-06-05 09:38:59",
        "version": "legacy",
        "fee_in_sol": 5e-06,
        "compute_units_consumed": 150,
        "previous_block_hash": "9btmmEec1hUJnx8MaQvMhZgy9EyjhChkfmNxAjBmeJgV",
        "signers": [],
        "from": {
            "address": "ANVUJaJoVaJZELtV2AvRp7V5qPV1B84o29zAwDhPj1c2",
            "balance_before": 1.819730596,
            "balance_after": 1.819725578,
            "balance_change": -5.018e-06
        },
        "to": [
            {
                "address": "4PkiqJkUvxr9P8C1UsMqGN8NJsUcep9GahDRLfmeu8UK",
                "balance_before": 1.819730596,
                "balance_after": 1.819725578,
                "balance_change": 5.018e-06
            }
        ],
        "instructions": [
            {
                "program_id": "11111111111111111111111111111111",
                "type": "transfer",
                "info": {
                    "destination": "4PkiqJkUvxr9P8C1UsMqGN8NJsUcep9GahDRLfmeu8UK",
                    "lamports": 18,
                    "source": "ANVUJaJoVaJZELtV2AvRp7V5qPV1B84o29zAwDhPj1c2"
                }
            }
        ]
    },
    {
        "signature": "Hh1kvrMzEV74HUV3BUv19nqqG6eMsxoEsKPNQhB4xCDzRQstrfD4dfTeLQKg374badS4DUazspqNbzA7cTvgBPz",
        "block": 385526371,
        "timestamp": "2025-06-05 09:38:59",
        "version": "legacy",
        "fee_in_sol": 5e-06,
        "compute_units_consumed": 150,
        "previous_block_hash": "6qi14kXaHH8tXc9z82e7LHsW8hyY9zCe8RAJzVX4xtXL",
        "signers": [],
        "from": {
            "address": "ANVUJaJoVaJZELtV2AvRp7V5qPV1B84o29zAwDhPj1c2",
            "balance_before": 1.81973561,
            "balance_after": 1.819730596,
            "balance_change": -5.014e-06
        },
        "to": [
            {
                "address": "4PkiqJkUvxr9P8C1UsMqGN8NJsUcep9GahDRLfmeu8UK",
                "balance_before": 1.81973561,
                "balance_after": 1.819730596,
                "balance_change": 5.014e-06
            }
        ],
        "instructions": [
            {
                "program_id": "11111111111111111111111111111111",
                "type": "transfer",
                "info": {
                    "destination": "4PkiqJkUvxr9P8C1UsMqGN8NJsUcep9GahDRLfmeu8UK",
                    "lamports": 14,
                    "source": "ANVUJaJoVaJZELtV2AvRp7V5qPV1B84o29zAwDhPj1c2"
                }
            }
        ]
    },
    {
        "signature": "2gTGuBKUC7ZN3e4sdGexUV1rYAMiNXxysqNFzN3DKFMBx5j7ktXeEQKaWf1BhBBeJv2HqcbukUGWDD9AWYjjf5Zp",
        "block": 385526370,
        "timestamp": "2025-06-05 09:38:59",
        "version": "legacy",
        "fee_in_sol": 5e-06,
        "compute_units_consumed": 150,
        "previous_block_hash": "D1F9SLjpqkUGfx3FjFYaAbuTo7Bber5RxqExZ8NbPza2",
        "signers": [],
        "from": {
            "address": "ANVUJaJoVaJZELtV2AvRp7V5qPV1B84o29zAwDhPj1c2",
            "balance_before": 1.819740616,
            "balance_after": 1.81973561,
            "balance_change": -5.006e-06
        },
        "to": [
            {
                "address": "4PkiqJkUvxr9P8C1UsMqGN8NJsUcep9GahDRLfmeu8UK",
                "balance_before": 1.819740616,
                "balance_after": 1.81973561,
                "balance_change": 5.006e-06
            }
        ],
        "instructions": [
            {
                "program_id": "11111111111111111111111111111111",
                "type": "transfer",
                "info": {
                    "destination": "4PkiqJkUvxr9P8C1UsMqGN8NJsUcep9GahDRLfmeu8UK",
                    "lamports": 6,
                    "source": "ANVUJaJoVaJZELtV2AvRp7V5qPV1B84o29zAwDhPj1c2"
                }
            }
        ]
    },
    {
        "signature": "2jWDjgJWCPdhcyjDdZkGGz8SBeqSXpSqSh1ShVfoUpdTLBAhpAMWRtzY8wHHrkBcagjCKDmHv5i8891HxXqLGSEF",
        "block": 385526370,
        "timestamp": "2025-06-05 09:38:59",
        "version": "legacy",
        "fee_in_sol": 5e-06,
        "compute_units_consumed": 150,
        "previous_block_hash": "4JmXTZf9buNdsVy69HDL8kDxrvLcvkbiDgW57HY218oN",
        "signers": [],
        "from": {
            "address": "ANVUJaJoVaJZELtV2AvRp7V5qPV1B84o29zAwDhPj1c2",
            "balance_before": 1.819745624,
            "balance_after": 1.819740616,
            "balance_change": -5.008e-06
        },
        "to": [
            {
                "address": "4PkiqJkUvxr9P8C1UsMqGN8NJsUcep9GahDRLfmeu8UK",
                "balance_before": 1.819745624,
                "balance_after": 1.819740616,
                "balance_change": 5.008e-06
            }
        ],
        "instructions": [
            {
                "program_id": "11111111111111111111111111111111",
                "type": "transfer",
                "info": {
                    "destination": "4PkiqJkUvxr9P8C1UsMqGN8NJsUcep9GahDRLfmeu8UK",
                    "lamports": 8,
                    "source": "ANVUJaJoVaJZELtV2AvRp7V5qPV1B84o29zAwDhPj1c2"
                }
            }
        ]
    },
    {
        "signature": "4bMG16qvRAqQidP7YvHLS3K7qtiGnsrQ4dbhccSUFrafcnJxVCeVDPp9PK4rdf6LEJiyNKdRdiwqxJH2QBipiojL",
        "block": 385526370,
        "timestamp": "2025-06-05 09:38:59",
        "version": "legacy",
        "fee_in_sol": 5e-06,
        "compute_units_consumed": 150,
        "previous_block_hash": "9pgTgA9StCHjowr18Tb58XGoWcJmhYmCzdxoeAGtaEhL",
        "signers": [],
        "from": {
            "address": "4PkiqJkUvxr9P8C1UsMqGN8NJsUcep9GahDRLfmeu8UK",
            "balance_before": 10.402136613,
            "balance_after": 10.402131612,
            "balance_change": -5.001e-06
        },
        "to": [
            {
                "address": "ANVUJaJoVaJZELtV2AvRp7V5qPV1B84o29zAwDhPj1c2",
                "balance_before": 10.402136613,
                "balance_after": 10.402131612,
                "balance_change": 5.001e-06
            }
        ],
        "instructions": [
            {
                "program_id": "11111111111111111111111111111111",
                "type": "transfer",
                "info": {
                    "destination": "ANVUJaJoVaJZELtV2AvRp7V5qPV1B84o29zAwDhPj1c2",
                    "lamports": 1,
                    "source": "4PkiqJkUvxr9P8C1UsMqGN8NJsUcep9GahDRLfmeu8UK"
                }
            }
        ]
    },
    {
        "signature": "3FxWntfFLRzjfPmELAW7vqp7FBXa3H1MWXk8bk4Nra3F8RsKwV9bPYYai1hReqyuEqfDkW3QvSNJSpHdn9ASEj7K",
        "block": 385526370,
        "timestamp": "2025-06-05 09:38:59",
        "version": "legacy",
        "fee_in_sol": 5e-06,
        "compute_units_consumed": 150,
        "previous_block_hash": "6iNMerZJ9tHo94PpmDqdaRjn818NFkUbSxGR9qLuJtYJ",
        "signers": [],
        "from": {
            "address": "ANVUJaJoVaJZELtV2AvRp7V5qPV1B84o29zAwDhPj1c2",
            "balance_before": 1.819750633,
            "balance_after": 1.819745623,
            "balance_change": -5.01e-06
        },
        "to": [
            {
                "address": "4PkiqJkUvxr9P8C1UsMqGN8NJsUcep9GahDRLfmeu8UK",
                "balance_before": 1.819750633,
                "balance_after": 1.819745623,
                "balance_change": 5.01e-06
            }
        ],
        "instructions": [
            {
                "program_id": "11111111111111111111111111111111",
                "type": "transfer",
                "info": {
                    "destination": "4PkiqJkUvxr9P8C1UsMqGN8NJsUcep9GahDRLfmeu8UK",
                    "lamports": 10,
                    "source": "ANVUJaJoVaJZELtV2AvRp7V5qPV1B84o29zAwDhPj1c2"
                }
            }
        ]
    },
    {
        "signature": "6tKGnbWiUCpeLG5cFr9kUXBCvWttghLkT9ekiwMEcVvQnFhJHLeMoUXDyHEE83uFTrdJHGLr6Q6uTvmWn8fKpzn",
        "block": 385526370,
        "timestamp": "2025-06-05 09:38:59",
        "version": "legacy",
        "fee_in_sol": 5e-06,
        "compute_units_consumed": 150,
        "previous_block_hash": "6oBNiMModUCpBMu95N2rb5ZLHdoNJFySq8THVK9xqDqA",
        "signers": [],
        "from": {
            "address": "4PkiqJkUvxr9P8C1UsMqGN8NJsUcep9GahDRLfmeu8UK",
            "balance_before": 10.402141606,
            "balance_after": 10.402136603,
            "balance_change": -5.003e-06
        },
        "to": [
            {
                "address": "ANVUJaJoVaJZELtV2AvRp7V5qPV1B84o29zAwDhPj1c2",
                "balance_before": 10.402141606,
                "balance_after": 10.402136603,
                "balance_change": 5.003e-06
            }
        ],
        "instructions": [
            {
                "program_id": "11111111111111111111111111111111",
                "type": "transfer",
                "info": {
                    "destination": "ANVUJaJoVaJZELtV2AvRp7V5qPV1B84o29zAwDhPj1c2",
                    "lamports": 3,
                    "source": "4PkiqJkUvxr9P8C1UsMqGN8NJsUcep9GahDRLfmeu8UK"
                }
            }
        ]
    },
    {
        "signature": "52arLp18pswReU4ifKYg7wHkiyjApuhmZENkBzp5iRftvetWzbo8Giouz2aeMBrNfbt3xEpERDGnC3LDGB7RqgDN",
        "block": 385526368,
        "timestamp": "2025-06-05 09:38:58",
        "version": "legacy",
        "fee_in_sol": 5e-06,
        "compute_units_consumed": 150,
        "previous_block_hash": "GYiEUxgPaHjBXHqc2i6ayZpbXVNN8LEWEPdrqy5p3YpU",
        "signers": [],
        "from": {
            "address": "4PkiqJkUvxr9P8C1UsMqGN8NJsUcep9GahDRLfmeu8UK",
            "balance_before": 10.402146613,
            "balance_after": 10.402141606,
            "balance_change": -5.007e-06
        },
        "to": [
            {
                "address": "ANVUJaJoVaJZELtV2AvRp7V5qPV1B84o29zAwDhPj1c2",
                "balance_before": 10.402146613,
                "balance_after": 10.402141606,
                "balance_change": 5.007e-06
            }
        ],
        "instructions": [
            {
                "program_id": "11111111111111111111111111111111",
                "type": "transfer",
                "info": {
                    "destination": "ANVUJaJoVaJZELtV2AvRp7V5qPV1B84o29zAwDhPj1c2",
                    "lamports": 7,
                    "source": "4PkiqJkUvxr9P8C1UsMqGN8NJsUcep9GahDRLfmeu8UK"
                }
            }
        ]
    },
    {
        "signature": "5LhvVyu99mVVCdGPJYFyGKMXJ4oYd9pEPZWPbmghbXe6gjK3MVi9CAdrMfNnhLkKHG21xzdRvGKKwx9Vq4V1JG5S",
        "block": 385526368,
        "timestamp": "2025-06-05 09:38:58",
        "version": "legacy",
        "fee_in_sol": 5e-06,
        "compute_units_consumed": 150,
        "previous_block_hash": "ERXs87zUz6rqVBrWpFgHz7Vn3MXWgb32h1ghUf8YgK4Q",
        "signers": [],
        "from": {
            "address": "4PkiqJkUvxr9P8C1UsMqGN8NJsUcep9GahDRLfmeu8UK",
            "balance_before": 10.402151628,
            "balance_after": 10.402146613,
            "balance_change": -5.015e-06
        },
        "to": [
            {
                "address": "ANVUJaJoVaJZELtV2AvRp7V5qPV1B84o29zAwDhPj1c2",
                "balance_before": 10.402151628,
                "balance_after": 10.402146613,
                "balance_change": 5.015e-06
            }
        ],
        "instructions": [
            {
                "program_id": "11111111111111111111111111111111",
                "type": "transfer",
                "info": {
                    "destination": "ANVUJaJoVaJZELtV2AvRp7V5qPV1B84o29zAwDhPj1c2",
                    "lamports": 15,
                    "source": "4PkiqJkUvxr9P8C1UsMqGN8NJsUcep9GahDRLfmeu8UK"
                }
            }
        ]
    },
    {
        "signature": "448G7CrgLLyCYSpEx9gX14uF2LGMTYPRKH1hJTaWEGm6u2oozb4NgfEqQzhLaNFAkx2EBYE2rRuHiBVwkMteUoS5",
        "block": 385526368,
        "timestamp": "2025-06-05 09:38:58",
        "version": "legacy",
        "fee_in_sol": 5e-06,
        "compute_units_consumed": 150,
        "previous_block_hash": "6qi14kXaHH8tXc9z82e7LHsW8hyY9zCe8RAJzVX4xtXL",
        "signers": [],
        "from": {
            "address": "4PkiqJkUvxr9P8C1UsMqGN8NJsUcep9GahDRLfmeu8UK",
            "balance_before": 10.402156637,
            "balance_after": 10.402151628,
            "balance_change": -5.009e-06
        },
        "to": [
            {
                "address": "ANVUJaJoVaJZELtV2AvRp7V5qPV1B84o29zAwDhPj1c2",
                "balance_before": 10.402156637,
                "balance_after": 10.402151628,
                "balance_change": 5.009e-06
            }
        ],
        "instructions": [
            {
                "program_id": "11111111111111111111111111111111",
                "type": "transfer",
                "info": {
                    "destination": "ANVUJaJoVaJZELtV2AvRp7V5qPV1B84o29zAwDhPj1c2",
                    "lamports": 9,
                    "source": "4PkiqJkUvxr9P8C1UsMqGN8NJsUcep9GahDRLfmeu8UK"
                }
            }
        ]
    },
    {
        "signature": "Vx3V3uJddv2vEMyjZ2f3Lugd81VwkFEuKcGHR6XacWVum2XtsVF6mQQbT8PZum3LE3JgpPU74DwX6krSiKzPjPc",
        "block": 385526368,
        "timestamp": "2025-06-05 09:38:58",
        "version": "legacy",
        "fee_in_sol": 5e-06,
        "compute_units_consumed": 150,
        "previous_block_hash": "FmF9j99QXw84kaWH8kJeqZjdL9DD2iYGtwJU4wh3omd6",
        "signers": [],
        "from": {
            "address": "ANVUJaJoVaJZELtV2AvRp7V5qPV1B84o29zAwDhPj1c2",
            "balance_before": 1.819755617,
            "balance_after": 1.819750599,
            "balance_change": -5.018e-06
        },
        "to": [
            {
                "address": "4PkiqJkUvxr9P8C1UsMqGN8NJsUcep9GahDRLfmeu8UK",
                "balance_before": 1.819755617,
                "balance_after": 1.819750599,
                "balance_change": 5.018e-06
            }
        ],
        "instructions": [
            {
                "program_id": "11111111111111111111111111111111",
                "type": "transfer",
                "info": {
                    "destination": "4PkiqJkUvxr9P8C1UsMqGN8NJsUcep9GahDRLfmeu8UK",
                    "lamports": 18,
                    "source": "ANVUJaJoVaJZELtV2AvRp7V5qPV1B84o29zAwDhPj1c2"
                }
            }
        ]
    },
    {
        "signature": "4rCuTo4RbWBpWt6bj5NTkLb63312NE4rwTffBMFqwZD8ds7HK2peTMzXvQSX63XPNzWGBei68fd78bwikLoTfqMh",
        "block": 385526368,
        "timestamp": "2025-06-05 09:38:58",
        "version": "legacy",
        "fee_in_sol": 5e-06,
        "compute_units_consumed": 150,
        "previous_block_hash": "9btmmEec1hUJnx8MaQvMhZgy9EyjhChkfmNxAjBmeJgV",
        "signers": [],
        "from": {
            "address": "4PkiqJkUvxr9P8C1UsMqGN8NJsUcep9GahDRLfmeu8UK",
            "balance_before": 10.402161632,
            "balance_after": 10.402156619,
            "balance_change": -5.013e-06
        },
        "to": [
            {
                "address": "ANVUJaJoVaJZELtV2AvRp7V5qPV1B84o29zAwDhPj1c2",
                "balance_before": 10.402161632,
                "balance_after": 10.402156619,
                "balance_change": 5.013e-06
            }
        ],
        "instructions": [
            {
                "program_id": "11111111111111111111111111111111",
                "type": "transfer",
                "info": {
                    "destination": "ANVUJaJoVaJZELtV2AvRp7V5qPV1B84o29zAwDhPj1c2",
                    "lamports": 13,
                    "source": "4PkiqJkUvxr9P8C1UsMqGN8NJsUcep9GahDRLfmeu8UK"
                }
            }
        ]
    },
    {
        "signature": "3WCE6Ti4PY7eu3owrtCb8eNoFYKCiUtqAfeR672uwkQNrd4tw9sUQqDomGHGyF6eDK3H5fyE8Gr3PuQY3wTMa66C",
        "block": 385526368,
        "timestamp": "2025-06-05 09:38:58",
        "version": "legacy",
        "fee_in_sol": 5e-06,
        "compute_units_consumed": 150,
        "previous_block_hash": "4JmXTZf9buNdsVy69HDL8kDxrvLcvkbiDgW57HY218oN",
        "signers": [],
        "from": {
            "address": "4PkiqJkUvxr9P8C1UsMqGN8NJsUcep9GahDRLfmeu8UK",
            "balance_before": 10.402166635,
            "balance_after": 10.402161632,
            "balance_change": -5.003e-06
        },
        "to": [
            {
                "address": "ANVUJaJoVaJZELtV2AvRp7V5qPV1B84o29zAwDhPj1c2",
                "balance_before": 10.402166635,
                "balance_after": 10.402161632,
                "balance_change": 5.003e-06
            }
        ],
        "instructions": [
            {
                "program_id": "11111111111111111111111111111111",
                "type": "transfer",
                "info": {
                    "destination": "ANVUJaJoVaJZELtV2AvRp7V5qPV1B84o29zAwDhPj1c2",
                    "lamports": 3,
                    "source": "4PkiqJkUvxr9P8C1UsMqGN8NJsUcep9GahDRLfmeu8UK"
                }
            }
        ]
    },
    {
        "signature": "2MyqSR5GBirwkGPh3oawva9iggSr1AAM8X4ZGvNwDnboBAjyBYzm26bo7fXezPtViQ72RYPYtLfFxsA4WS6oGKnu",
        "block": 385526368,
        "timestamp": "2025-06-05 09:38:58",
        "version": "legacy",
        "fee_in_sol": 5e-06,
        "compute_units_consumed": 150,
        "previous_block_hash": "6iNMerZJ9tHo94PpmDqdaRjn818NFkUbSxGR9qLuJtYJ",
        "signers": [],
        "from": {
            "address": "4PkiqJkUvxr9P8C1UsMqGN8NJsUcep9GahDRLfmeu8UK",
            "balance_before": 10.40217164,
            "balance_after": 10.402166635,
            "balance_change": -5.005e-06
        },
        "to": [
            {
                "address": "ANVUJaJoVaJZELtV2AvRp7V5qPV1B84o29zAwDhPj1c2",
                "balance_before": 10.40217164,
                "balance_after": 10.402166635,
                "balance_change": 5.005e-06
            }
        ],
        "instructions": [
            {
                "program_id": "11111111111111111111111111111111",
                "type": "transfer",
                "info": {
                    "destination": "ANVUJaJoVaJZELtV2AvRp7V5qPV1B84o29zAwDhPj1c2",
                    "lamports": 5,
                    "source": "4PkiqJkUvxr9P8C1UsMqGN8NJsUcep9GahDRLfmeu8UK"
                }
            }
        ]
    },
    {
        "signature": "2uBb5jKnGtFY8icH5ZdA9GkQtzwFmD4PEPb1h3xxhP6FrD9P3Mne17bPrrkcuKwSA4ws7s49gZbrfwgzk3wMQzGE",
        "block": 385526368,
        "timestamp": "2025-06-05 09:38:58",
        "version": "legacy",
        "fee_in_sol": 5e-06,
        "compute_units_consumed": 150,
        "previous_block_hash": "A8mFdZJirqpKLovdmaaN4RLQWke24HLShMz4h2BPEvRV",
        "signers": [],
        "from": {
            "address": "4PkiqJkUvxr9P8C1UsMqGN8NJsUcep9GahDRLfmeu8UK",
            "balance_before": 10.402176651,
            "balance_after": 10.40217164,
            "balance_change": -5.011e-06
        },
        "to": [
            {
                "address": "ANVUJaJoVaJZELtV2AvRp7V5qPV1B84o29zAwDhPj1c2",
                "balance_before": 10.402176651,
                "balance_after": 10.40217164,
                "balance_change": 5.011e-06
            }
        ],
        "instructions": [
            {
                "program_id": "11111111111111111111111111111111",
                "type": "transfer",
                "info": {
                    "destination": "ANVUJaJoVaJZELtV2AvRp7V5qPV1B84o29zAwDhPj1c2",
                    "lamports": 11,
                    "source": "4PkiqJkUvxr9P8C1UsMqGN8NJsUcep9GahDRLfmeu8UK"
                }
            }
        ]
    },
    {
        "signature": "2pKi2FdNniTWUa2xAX4doJojb4LgXJLaVFbadqYsMbxSQgCiHbP2vUyqfTNKEvCWxbRJ4PfncbpuQVcT9WaQu9VV",
        "block": 385526367,
        "timestamp": "2025-06-05 09:38:57",
        "version": "legacy",
        "fee_in_sol": 5e-06,
        "compute_units_consumed": 150,
        "previous_block_hash": "D1F9SLjpqkUGfx3FjFYaAbuTo7Bber5RxqExZ8NbPza2",
        "signers": [],
        "from": {
            "address": "4PkiqJkUvxr9P8C1UsMqGN8NJsUcep9GahDRLfmeu8UK",
            "balance_before": 10.402181652,
            "balance_after": 10.402176651,
            "balance_change": -5.001e-06
        },
        "to": [
            {
                "address": "ANVUJaJoVaJZELtV2AvRp7V5qPV1B84o29zAwDhPj1c2",
                "balance_before": 10.402181652,
                "balance_after": 10.402176651,
                "balance_change": 5.001e-06
            }
        ],
        "instructions": [
            {
                "program_id": "11111111111111111111111111111111",
                "type": "transfer",
                "info": {
                    "destination": "ANVUJaJoVaJZELtV2AvRp7V5qPV1B84o29zAwDhPj1c2",
                    "lamports": 1,
                    "source": "4PkiqJkUvxr9P8C1UsMqGN8NJsUcep9GahDRLfmeu8UK"
                }
            }
        ]
    },
    {
        "signature": "3NaxBfFWS63dQjqBBZHabXHdNFPWCFQUJrHz92AS3wwtDUHvMKoX3Mujr6ziAfZ6SXNrQLHUhToQrPmts9jLtDug",
        "block": 385526367,
        "timestamp": "2025-06-05 09:38:57",
        "version": "legacy",
        "fee_in_sol": 5e-06,
        "compute_units_consumed": 150,
        "previous_block_hash": "9j3R44mnBNScib6NgPKyzYvfgUgA6RctVGUNptM5XEYJ",
        "signers": [],
        "from": {
            "address": "ANVUJaJoVaJZELtV2AvRp7V5qPV1B84o29zAwDhPj1c2",
            "balance_before": 1.819760604,
            "balance_after": 1.819755584,
            "balance_change": -5.02e-06
        },
        "to": [
            {
                "address": "4PkiqJkUvxr9P8C1UsMqGN8NJsUcep9GahDRLfmeu8UK",
                "balance_before": 1.819760604,
                "balance_after": 1.819755584,
                "balance_change": 5.02e-06
            }
        ],
        "instructions": [
            {
                "program_id": "11111111111111111111111111111111",
                "type": "transfer",
                "info": {
                    "destination": "4PkiqJkUvxr9P8C1UsMqGN8NJsUcep9GahDRLfmeu8UK",
                    "lamports": 20,
                    "source": "ANVUJaJoVaJZELtV2AvRp7V5qPV1B84o29zAwDhPj1c2"
                }
            }
        ]
    },
    {
        "signature": "4Z9VQYNBZkTsvgrU2Dr6GQLHnJuD86VzUjKAcURCUGaACunc66cnLw5u9y547y8CWfQiZEwGU8AFNbdgoSZApVJP",
        "block": 385526365,
        "timestamp": "2025-06-05 09:38:57",
        "version": "legacy",
        "fee_in_sol": 5e-06,
        "compute_units_consumed": 150,
        "previous_block_hash": "A8mFdZJirqpKLovdmaaN4RLQWke24HLShMz4h2BPEvRV",
        "signers": [],
        "from": {
            "address": "4PkiqJkUvxr9P8C1UsMqGN8NJsUcep9GahDRLfmeu8UK",
            "balance_before": 10.402186637,
            "balance_after": 10.402181632,
            "balance_change": -5.005e-06
        },
        "to": [
            {
                "address": "ANVUJaJoVaJZELtV2AvRp7V5qPV1B84o29zAwDhPj1c2",
                "balance_before": 10.402186637,
                "balance_after": 10.402181632,
                "balance_change": 5.005e-06
            }
        ],
        "instructions": [
            {
                "program_id": "11111111111111111111111111111111",
                "type": "transfer",
                "info": {
                    "destination": "ANVUJaJoVaJZELtV2AvRp7V5qPV1B84o29zAwDhPj1c2",
                    "lamports": 5,
                    "source": "4PkiqJkUvxr9P8C1UsMqGN8NJsUcep9GahDRLfmeu8UK"
                }
            }
        ]
    },
    {
        "signature": "63XmRrj1jPq6WzgFevG3S9F7CzkaKLwEr9TyLwyQTjHpCKCJWr4y7Z1E6wjUhVTHLoaJMueKYFzoMENcjZic4Cmw",
        "block": 385526365,
        "timestamp": "2025-06-05 09:38:57",
        "version": "legacy",
        "fee_in_sol": 5e-06,
        "compute_units_consumed": 150,
        "previous_block_hash": "GYiEUxgPaHjBXHqc2i6ayZpbXVNN8LEWEPdrqy5p3YpU",
        "signers": [],
        "from": {
            "address": "4PkiqJkUvxr9P8C1UsMqGN8NJsUcep9GahDRLfmeu8UK",
            "balance_before": 10.402191638,
            "balance_after": 10.402186637,
            "balance_change": -5.001e-06
        },
        "to": [
            {
                "address": "ANVUJaJoVaJZELtV2AvRp7V5qPV1B84o29zAwDhPj1c2",
                "balance_before": 10.402191638,
                "balance_after": 10.402186637,
                "balance_change": 5.001e-06
            }
        ],
        "instructions": [
            {
                "program_id": "11111111111111111111111111111111",
                "type": "transfer",
                "info": {
                    "destination": "ANVUJaJoVaJZELtV2AvRp7V5qPV1B84o29zAwDhPj1c2",
                    "lamports": 1,
                    "source": "4PkiqJkUvxr9P8C1UsMqGN8NJsUcep9GahDRLfmeu8UK"
                }
            }
        ]
    },
    {
        "signature": "tN6kX2Nb3Hv7ejZwrDt8uM5bw1mfJvbYKnTKfbXhM5Uh1jzNj69Z94pbzE2ciFssxCt5ivrsvUqmweZ1cZHFLLP",
        "block": 385526365,
        "timestamp": "2025-06-05 09:38:57",
        "version": "legacy",
        "fee_in_sol": 5e-06,
        "compute_units_consumed": 150,
        "previous_block_hash": "ERXs87zUz6rqVBrWpFgHz7Vn3MXWgb32h1ghUf8YgK4Q",
        "signers": [],
        "from": {
            "address": "4PkiqJkUvxr9P8C1UsMqGN8NJsUcep9GahDRLfmeu8UK",
            "balance_before": 10.402196647,
            "balance_after": 10.402191638,
            "balance_change": -5.009e-06
        },
        "to": [
            {
                "address": "ANVUJaJoVaJZELtV2AvRp7V5qPV1B84o29zAwDhPj1c2",
                "balance_before": 10.402196647,
                "balance_after": 10.402191638,
                "balance_change": 5.009e-06
            }
        ],
        "instructions": [
            {
                "program_id": "11111111111111111111111111111111",
                "type": "transfer",
                "info": {
                    "destination": "ANVUJaJoVaJZELtV2AvRp7V5qPV1B84o29zAwDhPj1c2",
                    "lamports": 9,
                    "source": "4PkiqJkUvxr9P8C1UsMqGN8NJsUcep9GahDRLfmeu8UK"
                }
            }
        ]
    },
    {
        "signature": "2V6yW8qnGjExBoZx81CH4bL3ifjPrR2nvr9j95j9Zf7cXayw6ep9V3SAyaANdkBY4asfcF1fvN9fCdqunM7cXgZn",
        "block": 385526365,
        "timestamp": "2025-06-05 09:38:57",
        "version": "legacy",
        "fee_in_sol": 5e-06,
        "compute_units_consumed": 150,
        "previous_block_hash": "9btmmEec1hUJnx8MaQvMhZgy9EyjhChkfmNxAjBmeJgV",
        "signers": [],
        "from": {
            "address": "4PkiqJkUvxr9P8C1UsMqGN8NJsUcep9GahDRLfmeu8UK",
            "balance_before": 10.402201654,
            "balance_after": 10.402196647,
            "balance_change": -5.007e-06
        },
        "to": [
            {
                "address": "ANVUJaJoVaJZELtV2AvRp7V5qPV1B84o29zAwDhPj1c2",
                "balance_before": 10.402201654,
                "balance_after": 10.402196647,
                "balance_change": 5.007e-06
            }
        ],
        "instructions": [
            {
                "program_id": "11111111111111111111111111111111",
                "type": "transfer",
                "info": {
                    "destination": "ANVUJaJoVaJZELtV2AvRp7V5qPV1B84o29zAwDhPj1c2",
                    "lamports": 7,
                    "source": "4PkiqJkUvxr9P8C1UsMqGN8NJsUcep9GahDRLfmeu8UK"
                }
            }
        ]
    },
    {
        "signature": "29CcepReyvmUrDduRpba1mGqu6jRwfgimydjASTAoU4GV9U6FycgBuP8Phn1Fjbk7xSDEPqNk98qxKRLsN8Uao5k",
        "block": 385526365,
        "timestamp": "2025-06-05 09:38:57",
        "version": "legacy",
        "fee_in_sol": 5e-06,
        "compute_units_consumed": 150,
        "previous_block_hash": "9j3R44mnBNScib6NgPKyzYvfgUgA6RctVGUNptM5XEYJ",
        "signers": [],
        "from": {
            "address": "ANVUJaJoVaJZELtV2AvRp7V5qPV1B84o29zAwDhPj1c2",
            "balance_before": 1.819765596,
            "balance_after": 1.819760582,
            "balance_change": -5.014e-06
        },
        "to": [
            {
                "address": "4PkiqJkUvxr9P8C1UsMqGN8NJsUcep9GahDRLfmeu8UK",
                "balance_before": 1.819765596,
                "balance_after": 1.819760582,
                "balance_change": 5.014e-06
            }
        ],
        "instructions": [
            {
                "program_id": "11111111111111111111111111111111",
                "type": "transfer",
                "info": {
                    "destination": "4PkiqJkUvxr9P8C1UsMqGN8NJsUcep9GahDRLfmeu8UK",
                    "lamports": 14,
                    "source": "ANVUJaJoVaJZELtV2AvRp7V5qPV1B84o29zAwDhPj1c2"
                }
            }
        ]
    },
    {
        "signature": "4yX63ad745Tbt6ieAaeuV42x777PGV9qYAyEsS8fNngpQ1Pt7iMjgzkXRVVnsuiszDePMAkXeixAqXTbqTBb8GqQ",
        "block": 385526365,
        "timestamp": "2025-06-05 09:38:57",
        "version": "legacy",
        "fee_in_sol": 5e-06,
        "compute_units_consumed": 150,
        "previous_block_hash": "6qi14kXaHH8tXc9z82e7LHsW8hyY9zCe8RAJzVX4xtXL",
        "signers": [],
        "from": {
            "address": "4PkiqJkUvxr9P8C1UsMqGN8NJsUcep9GahDRLfmeu8UK",
            "balance_before": 10.402206643,
            "balance_after": 10.40220164,
            "balance_change": -5.003e-06
        },
        "to": [
            {
                "address": "ANVUJaJoVaJZELtV2AvRp7V5qPV1B84o29zAwDhPj1c2",
                "balance_before": 10.402206643,
                "balance_after": 10.40220164,
                "balance_change": 5.003e-06
            }
        ],
        "instructions": [
            {
                "program_id": "11111111111111111111111111111111",
                "type": "transfer",
                "info": {
                    "destination": "ANVUJaJoVaJZELtV2AvRp7V5qPV1B84o29zAwDhPj1c2",
                    "lamports": 3,
                    "source": "4PkiqJkUvxr9P8C1UsMqGN8NJsUcep9GahDRLfmeu8UK"
                }
            }
        ]
    },
    {
        "signature": "42cMcgjSSuo1iEkyGxJv48nCPJSitJrfCneS7fg7d9ZSwtj4wUM1zSv9F2Pj9e8ZLecYVBDXiEzAKGVhUToHnTGt",
        "block": 385526365,
        "timestamp": "2025-06-05 09:38:57",
        "version": "legacy",
        "fee_in_sol": 5e-06,
        "compute_units_consumed": 150,
        "previous_block_hash": "C24axCpnQchE5dW7EeQ4m3HVonQHzi3pZqLwm39cgFsW",
        "signers": [],
        "from": {
            "address": "4PkiqJkUvxr9P8C1UsMqGN8NJsUcep9GahDRLfmeu8UK",
            "balance_before": 10.40221166,
            "balance_after": 10.402206643,
            "balance_change": -5.017e-06
        },
        "to": [
            {
                "address": "ANVUJaJoVaJZELtV2AvRp7V5qPV1B84o29zAwDhPj1c2",
                "balance_before": 10.40221166,
                "balance_after": 10.402206643,
                "balance_change": 5.017e-06
            }
        ],
        "instructions": [
            {
                "program_id": "11111111111111111111111111111111",
                "type": "transfer",
                "info": {
                    "destination": "ANVUJaJoVaJZELtV2AvRp7V5qPV1B84o29zAwDhPj1c2",
                    "lamports": 17,
                    "source": "4PkiqJkUvxr9P8C1UsMqGN8NJsUcep9GahDRLfmeu8UK"
                }
            }
        ]
    },
    {
        "signature": "35TsZkBAUaedbpm88hrhWhq5VUsopK3EJN87movQarNiMaygYeVoqtDU2hjJFNnEz17eYKniPfHDYwKHKJa8wMLp",
        "block": 385526365,
        "timestamp": "2025-06-05 09:38:57",
        "version": "legacy",
        "fee_in_sol": 5e-06,
        "compute_units_consumed": 150,
        "previous_block_hash": "FmF9j99QXw84kaWH8kJeqZjdL9DD2iYGtwJU4wh3omd6",
        "signers": [],
        "from": {
            "address": "ANVUJaJoVaJZELtV2AvRp7V5qPV1B84o29zAwDhPj1c2",
            "balance_before": 1.819770588,
            "balance_after": 1.819765576,
            "balance_change": -5.012e-06
        },
        "to": [
            {
                "address": "4PkiqJkUvxr9P8C1UsMqGN8NJsUcep9GahDRLfmeu8UK",
                "balance_before": 1.819770588,
                "balance_after": 1.819765576,
                "balance_change": 5.012e-06
            }
        ],
        "instructions": [
            {
                "program_id": "11111111111111111111111111111111",
                "type": "transfer",
                "info": {
                    "destination": "4PkiqJkUvxr9P8C1UsMqGN8NJsUcep9GahDRLfmeu8UK",
                    "lamports": 12,
                    "source": "ANVUJaJoVaJZELtV2AvRp7V5qPV1B84o29zAwDhPj1c2"
                }
            }
        ]
    },
    {
        "signature": "4uFaaxw5bqpxJczkQrf7Cdxop7WxREazCUFXMnjUjBtFVF1WXwvp2LdkeJGvxPegNHksjXYwjiF7jgJs8coZmMQa",
        "block": 385526365,
        "timestamp": "2025-06-05 09:38:57",
        "version": "legacy",
        "fee_in_sol": 5e-06,
        "compute_units_consumed": 150,
        "previous_block_hash": "HAwHCMUiT7D9YXzhEU1Auk6Avk84Lu4SBfhJ5Hzi8oQD",
        "signers": [],
        "from": {
            "address": "ANVUJaJoVaJZELtV2AvRp7V5qPV1B84o29zAwDhPj1c2",
            "balance_before": 1.819775608,
            "balance_after": 1.819770588,
            "balance_change": -5.02e-06
        },
        "to": [
            {
                "address": "4PkiqJkUvxr9P8C1UsMqGN8NJsUcep9GahDRLfmeu8UK",
                "balance_before": 1.819775608,
                "balance_after": 1.819770588,
                "balance_change": 5.02e-06
            }
        ],
        "instructions": [
            {
                "program_id": "11111111111111111111111111111111",
                "type": "transfer",
                "info": {
                    "destination": "4PkiqJkUvxr9P8C1UsMqGN8NJsUcep9GahDRLfmeu8UK",
                    "lamports": 20,
                    "source": "ANVUJaJoVaJZELtV2AvRp7V5qPV1B84o29zAwDhPj1c2"
                }
            }
        ]
    },
    {
        "signature": "jPs82iDoY6Z8n79pa4nfLvDPhhbt3iPc5KDG8fpnSTGm4N7VbP6Ti58gw5KVtzmGAVENhzABwhNiwjStpXeB9Ju",
        "block": 385526365,
        "timestamp": "2025-06-05 09:38:57",
        "version": "legacy",
        "fee_in_sol": 5e-06,
        "compute_units_consumed": 150,
        "previous_block_hash": "EFk2DmJyo4aSycV7iWRmtDX7SFaaBzfcnRavTALS87AD",
        "signers": [],
        "from": {
            "address": "4PkiqJkUvxr9P8C1UsMqGN8NJsUcep9GahDRLfmeu8UK",
            "balance_before": 10.402216649,
            "balance_after": 10.402211628,
            "balance_change": -5.021e-06
        },
        "to": [
            {
                "address": "ANVUJaJoVaJZELtV2AvRp7V5qPV1B84o29zAwDhPj1c2",
                "balance_before": 10.402216649,
                "balance_after": 10.402211628,
                "balance_change": 5.021e-06
            }
        ],
        "instructions": [
            {
                "program_id": "11111111111111111111111111111111",
                "type": "transfer",
                "info": {
                    "destination": "ANVUJaJoVaJZELtV2AvRp7V5qPV1B84o29zAwDhPj1c2",
                    "lamports": 21,
                    "source": "4PkiqJkUvxr9P8C1UsMqGN8NJsUcep9GahDRLfmeu8UK"
                }
            }
        ]
    },
    {
        "signature": "5CpmmN3fPV3MV1VtA8andCk72gBpNwdeBb5YnxJX1pbnR7KsYGGNrporJBZLsodkjSSQ28R4RTVmJwVDZ1VKWmHL",
        "block": 385526363,
        "timestamp": "2025-06-05 09:38:56",
        "version": "legacy",
        "fee_in_sol": 5e-06,
        "compute_units_consumed": 150,
        "previous_block_hash": "EFk2DmJyo4aSycV7iWRmtDX7SFaaBzfcnRavTALS87AD",
        "signers": [],
        "from": {
            "address": "ANVUJaJoVaJZELtV2AvRp7V5qPV1B84o29zAwDhPj1c2",
            "balance_before": 1.819780603,
            "balance_after": 1.819775587,
            "balance_change": -5.016e-06
        },
        "to": [
            {
                "address": "4PkiqJkUvxr9P8C1UsMqGN8NJsUcep9GahDRLfmeu8UK",
                "balance_before": 1.819780603,
                "balance_after": 1.819775587,
                "balance_change": 5.016e-06
            }
        ],
        "instructions": [
            {
                "program_id": "11111111111111111111111111111111",
                "type": "transfer",
                "info": {
                    "destination": "4PkiqJkUvxr9P8C1UsMqGN8NJsUcep9GahDRLfmeu8UK",
                    "lamports": 16,
                    "source": "ANVUJaJoVaJZELtV2AvRp7V5qPV1B84o29zAwDhPj1c2"
                }
            }
        ]
    },
    {
        "signature": "3Apnja6Q3k5iit2ucevPRjvmV8guZyFo9bF6LQzPn2iBoXQhnMQ2LuJesv3vUUubbygfh9vCjpeuTjRLXFAp3gAg",
        "block": 385526363,
        "timestamp": "2025-06-05 09:38:56",
        "version": "legacy",
        "fee_in_sol": 5e-06,
        "compute_units_consumed": 150,
        "previous_block_hash": "ERXs87zUz6rqVBrWpFgHz7Vn3MXWgb32h1ghUf8YgK4Q",
        "signers": [],
        "from": {
            "address": "4PkiqJkUvxr9P8C1UsMqGN8NJsUcep9GahDRLfmeu8UK",
            "balance_before": 10.402221636,
            "balance_after": 10.402216633,
            "balance_change": -5.003e-06
        },
        "to": [
            {
                "address": "ANVUJaJoVaJZELtV2AvRp7V5qPV1B84o29zAwDhPj1c2",
                "balance_before": 10.402221636,
                "balance_after": 10.402216633,
                "balance_change": 5.003e-06
            }
        ],
        "instructions": [
            {
                "program_id": "11111111111111111111111111111111",
                "type": "transfer",
                "info": {
                    "destination": "ANVUJaJoVaJZELtV2AvRp7V5qPV1B84o29zAwDhPj1c2",
                    "lamports": 3,
                    "source": "4PkiqJkUvxr9P8C1UsMqGN8NJsUcep9GahDRLfmeu8UK"
                }
            }
        ]
    },
    {
        "signature": "9RFtqJwU2VtunQTmvecT3SwJ7i7j6yTPAS2zAgcA29sdgupihCBsjbrnxQVavWAWPo2ZYuTUg9NJ1HWpYCUQxkj",
        "block": 385526363,
        "timestamp": "2025-06-05 09:38:56",
        "version": "legacy",
        "fee_in_sol": 5e-06,
        "compute_units_consumed": 150,
        "previous_block_hash": "7QuPEi6RRSRn73bx7pTdFftfchxQKRWtAViJu4gji6S1",
        "signers": [],
        "from": {
            "address": "ANVUJaJoVaJZELtV2AvRp7V5qPV1B84o29zAwDhPj1c2",
            "balance_before": 1.81978562,
            "balance_after": 1.8197806,
            "balance_change": -5.02e-06
        },
        "to": [
            {
                "address": "4PkiqJkUvxr9P8C1UsMqGN8NJsUcep9GahDRLfmeu8UK",
                "balance_before": 1.81978562,
                "balance_after": 1.8197806,
                "balance_change": 5.02e-06
            }
        ],
        "instructions": [
            {
                "program_id": "11111111111111111111111111111111",
                "type": "transfer",
                "info": {
                    "destination": "4PkiqJkUvxr9P8C1UsMqGN8NJsUcep9GahDRLfmeu8UK",
                    "lamports": 20,
                    "source": "ANVUJaJoVaJZELtV2AvRp7V5qPV1B84o29zAwDhPj1c2"
                }
            }
        ]
    },
    {
        "signature": "5kL1uDmXGUksdvtygc3aCNPjBKe3MnBrmL2m4zz52yVeeGpDSE9SGxy3UL16aRYqDTA7PFoMUGM3nH1pmvonXake",
        "block": 385526363,
        "timestamp": "2025-06-05 09:38:56",
        "version": "legacy",
        "fee_in_sol": 5e-06,
        "compute_units_consumed": 150,
        "previous_block_hash": "9btmmEec1hUJnx8MaQvMhZgy9EyjhChkfmNxAjBmeJgV",
        "signers": [],
        "from": {
            "address": "4PkiqJkUvxr9P8C1UsMqGN8NJsUcep9GahDRLfmeu8UK",
            "balance_before": 10.402226617,
            "balance_after": 10.402221616,
            "balance_change": -5.001e-06
        },
        "to": [
            {
                "address": "ANVUJaJoVaJZELtV2AvRp7V5qPV1B84o29zAwDhPj1c2",
                "balance_before": 10.402226617,
                "balance_after": 10.402221616,
                "balance_change": 5.001e-06
            }
        ],
        "instructions": [
            {
                "program_id": "11111111111111111111111111111111",
                "type": "transfer",
                "info": {
                    "destination": "ANVUJaJoVaJZELtV2AvRp7V5qPV1B84o29zAwDhPj1c2",
                    "lamports": 1,
                    "source": "4PkiqJkUvxr9P8C1UsMqGN8NJsUcep9GahDRLfmeu8UK"
                }
            }
        ]
    },
    {
        "signature": "5HgcwzSnBBtKZFhrYjfBLict5cZK5JpHawRHiRuCMHbiga8Sur3AFhz6fHUCLLuNzHA2csSmvfxmNYR31FMKq4gb",
        "block": 385526362,
        "timestamp": "2025-06-05 09:38:56",
        "version": "legacy",
        "fee_in_sol": 5e-06,
        "compute_units_consumed": 150,
        "previous_block_hash": "7wHY37QoEksBhYfmDcShgMPj72Wv2VeCbwoBnU5nB5kA",
        "signers": [],
        "from": {
            "address": "ANVUJaJoVaJZELtV2AvRp7V5qPV1B84o29zAwDhPj1c2",
            "balance_before": 1.819790637,
            "balance_after": 1.819785619,
            "balance_change": -5.018e-06
        },
        "to": [
            {
                "address": "4PkiqJkUvxr9P8C1UsMqGN8NJsUcep9GahDRLfmeu8UK",
                "balance_before": 1.819790637,
                "balance_after": 1.819785619,
                "balance_change": 5.018e-06
            }
        ],
        "instructions": [
            {
                "program_id": "11111111111111111111111111111111",
                "type": "transfer",
                "info": {
                    "destination": "4PkiqJkUvxr9P8C1UsMqGN8NJsUcep9GahDRLfmeu8UK",
                    "lamports": 18,
                    "source": "ANVUJaJoVaJZELtV2AvRp7V5qPV1B84o29zAwDhPj1c2"
                }
            }
        ]
    },
    {
        "signature": "FQS1LDRXiRK6U53S4NvSFJHYwcRu9NY6TZd5L9cwTi1TqsxLqTKKqvmGDizhQn1kTWA4gW3t5ursHjAxrEmKFjU",
        "block": 385526362,
        "timestamp": "2025-06-05 09:38:56",
        "version": "legacy",
        "fee_in_sol": 5e-06,
        "compute_units_consumed": 150,
        "previous_block_hash": "HAwHCMUiT7D9YXzhEU1Auk6Avk84Lu4SBfhJ5Hzi8oQD",
        "signers": [],
        "from": {
            "address": "4PkiqJkUvxr9P8C1UsMqGN8NJsUcep9GahDRLfmeu8UK",
            "balance_before": 10.402231612,
            "balance_after": 10.402226599,
            "balance_change": -5.013e-06
        },
        "to": [
            {
                "address": "ANVUJaJoVaJZELtV2AvRp7V5qPV1B84o29zAwDhPj1c2",
                "balance_before": 10.402231612,
                "balance_after": 10.402226599,
                "balance_change": 5.013e-06
            }
        ],
        "instructions": [
            {
                "program_id": "11111111111111111111111111111111",
                "type": "transfer",
                "info": {
                    "destination": "ANVUJaJoVaJZELtV2AvRp7V5qPV1B84o29zAwDhPj1c2",
                    "lamports": 13,
                    "source": "4PkiqJkUvxr9P8C1UsMqGN8NJsUcep9GahDRLfmeu8UK"
                }
            }
        ]
    },
    {
        "signature": "2uXu1MVzfdQPeFHmWyq1UpU35RjwqhNezBennK4tQ6KaTJ6JH1koTByLCYmnwCCEzKUYQmLJH7bs8ypfMwdqFL6F",
        "block": 385526362,
        "timestamp": "2025-06-05 09:38:56",
        "version": "legacy",
        "fee_in_sol": 5e-06,
        "compute_units_consumed": 150,
        "previous_block_hash": "C24axCpnQchE5dW7EeQ4m3HVonQHzi3pZqLwm39cgFsW",
        "signers": [],
        "from": {
            "address": "4PkiqJkUvxr9P8C1UsMqGN8NJsUcep9GahDRLfmeu8UK",
            "balance_before": 10.402236623,
            "balance_after": 10.402231612,
            "balance_change": -5.011e-06
        },
        "to": [
            {
                "address": "ANVUJaJoVaJZELtV2AvRp7V5qPV1B84o29zAwDhPj1c2",
                "balance_before": 10.402236623,
                "balance_after": 10.402231612,
                "balance_change": 5.011e-06
            }
        ],
        "instructions": [
            {
                "program_id": "11111111111111111111111111111111",
                "type": "transfer",
                "info": {
                    "destination": "ANVUJaJoVaJZELtV2AvRp7V5qPV1B84o29zAwDhPj1c2",
                    "lamports": 11,
                    "source": "4PkiqJkUvxr9P8C1UsMqGN8NJsUcep9GahDRLfmeu8UK"
                }
            }
        ]
    },
    {
        "signature": "PfkPaPL8SRB5HdhhtViy9nQSAcFf2zJvcNwRtyZgUX8ik43ga3t13XBATw2rjD4WhQ92bgNRYjKtC2eYNaqC3ar",
        "block": 385526362,
        "timestamp": "2025-06-05 09:38:56",
        "version": "legacy",
        "fee_in_sol": 5e-06,
        "compute_units_consumed": 150,
        "previous_block_hash": "FmF9j99QXw84kaWH8kJeqZjdL9DD2iYGtwJU4wh3omd6",
        "signers": [],
        "from": {
            "address": "ANVUJaJoVaJZELtV2AvRp7V5qPV1B84o29zAwDhPj1c2",
            "balance_before": 1.819795619,
            "balance_after": 1.819790613,
            "balance_change": -5.006e-06
        },
        "to": [
            {
                "address": "4PkiqJkUvxr9P8C1UsMqGN8NJsUcep9GahDRLfmeu8UK",
                "balance_before": 1.819795619,
                "balance_after": 1.819790613,
                "balance_change": 5.006e-06
            }
        ],
        "instructions": [
            {
                "program_id": "11111111111111111111111111111111",
                "type": "transfer",
                "info": {
                    "destination": "4PkiqJkUvxr9P8C1UsMqGN8NJsUcep9GahDRLfmeu8UK",
                    "lamports": 6,
                    "source": "ANVUJaJoVaJZELtV2AvRp7V5qPV1B84o29zAwDhPj1c2"
                }
            }
        ]
    },
    {
        "signature": "3RkByhRaHuWB6M7JTXYUn5UWxUsFfFvxKTY9UePEH8XUrL7rRDwtm4ZbN6P6xLWyXotUuv42g5eZM3CcfffuQqPt",
        "block": 385526362,
        "timestamp": "2025-06-05 09:38:56",
        "version": "legacy",
        "fee_in_sol": 5e-06,
        "compute_units_consumed": 150,
        "previous_block_hash": "9j3R44mnBNScib6NgPKyzYvfgUgA6RctVGUNptM5XEYJ",
        "signers": [],
        "from": {
            "address": "ANVUJaJoVaJZELtV2AvRp7V5qPV1B84o29zAwDhPj1c2",
            "balance_before": 1.819800627,
            "balance_after": 1.819795619,
            "balance_change": -5.008e-06
        },
        "to": [
            {
                "address": "4PkiqJkUvxr9P8C1UsMqGN8NJsUcep9GahDRLfmeu8UK",
                "balance_before": 1.819800627,
                "balance_after": 1.819795619,
                "balance_change": 5.008e-06
            }
        ],
        "instructions": [
            {
                "program_id": "11111111111111111111111111111111",
                "type": "transfer",
                "info": {
                    "destination": "4PkiqJkUvxr9P8C1UsMqGN8NJsUcep9GahDRLfmeu8UK",
                    "lamports": 8,
                    "source": "ANVUJaJoVaJZELtV2AvRp7V5qPV1B84o29zAwDhPj1c2"
                }
            }
        ]
    },
    {
        "signature": "5vo3Tbzca7RRkd7yGKT5gWhQV8nWjsfvpSJHqNc6ZepMxYgRsSknxd1Qt6yZ8dtS99CCQ9qU5ud8uMoAfg9pDapq",
        "block": 385526362,
        "timestamp": "2025-06-05 09:38:56",
        "version": "legacy",
        "fee_in_sol": 5e-06,
        "compute_units_consumed": 150,
        "previous_block_hash": "EFk2DmJyo4aSycV7iWRmtDX7SFaaBzfcnRavTALS87AD",
        "signers": [],
        "from": {
            "address": "4PkiqJkUvxr9P8C1UsMqGN8NJsUcep9GahDRLfmeu8UK",
            "balance_before": 10.402241624,
            "balance_after": 10.402236609,
            "balance_change": -5.015e-06
        },
        "to": [
            {
                "address": "ANVUJaJoVaJZELtV2AvRp7V5qPV1B84o29zAwDhPj1c2",
                "balance_before": 10.402241624,
                "balance_after": 10.402236609,
                "balance_change": 5.015e-06
            }
        ],
        "instructions": [
            {
                "program_id": "11111111111111111111111111111111",
                "type": "transfer",
                "info": {
                    "destination": "ANVUJaJoVaJZELtV2AvRp7V5qPV1B84o29zAwDhPj1c2",
                    "lamports": 15,
                    "source": "4PkiqJkUvxr9P8C1UsMqGN8NJsUcep9GahDRLfmeu8UK"
                }
            }
        ]
    }
]